{
  "type": "land_use_centroids",
  "count": 675,
  "features": [
    {
      "id": 204418085,
      "lat": 11.6457006,
      "lon": 76.070295,
      "type": "wood"
    },
    {
      "id": 204418088,
      "lat": 11.6062071,
      "lon": 76.1128521,
      "type": "forest"
    },
    {
      "id": 204418105,
      "lat": 11.6091617,
      "lon": 76.2040315,
      "type": "quarry"
    },
    {
      "id": 303894521,
      "lat": 11.5750405,
      "lon": 76.0567161,
      "type": "meadow"
    },
    {
      "id": 380928409,
      "lat": 11.5476716,
      "lon": 76.2040027,
      "type": "grass"
    },
    {
      "id": 387000779,
      "lat": 11.6054698,
      "lon": 76.0841291,
      "type": "commercial"
    },
    {
      "id": 387007047,
      "lat": 11.6344848,
      "lon": 76.19816,
      "type": "quarry"
    },
    {
      "id": 387007048,
      "lat": 11.6293821,
      "lon": 76.2015045,
      "type": "quarry"
    },
    {
      "id": 387007050,
      "lat": 11.6366418,
      "lon": 76.2073885,
      "type": "quarry"
    },
    {
      "id": 387007052,
      "lat": 11.5782024,
      "lon": 76.1634502,
      "type": "water"
    },
    {
      "id": 387007055,
      "lat": 11.641767,
      "lon": 76.1927316,
      "type": "quarry"
    },
    {
      "id": 387007058,
      "lat": 11.6392032,
      "lon": 76.1990475,
      "type": "quarry"
    },
    {
      "id": 387208808,
      "lat": 11.4223165,
      "lon": 76.1811294,
      "type": "wood"
    },
    {
      "id": 389046687,
      "lat": 11.6307809,
      "lon": 76.2303211,
      "type": "commercial"
    },
    {
      "id": 478018820,
      "lat": 11.5325153,
      "lon": 76.1302334,
      "type": "industrial"
    },
    {
      "id": 478021081,
      "lat": 11.4508824,
      "lon": 76.2381497,
      "type": "water"
    },
    {
      "id": 478021082,
      "lat": 11.456504,
      "lon": 76.2345039,
      "type": "water"
    },
    {
      "id": 478021083,
      "lat": 11.462597,
      "lon": 76.2310768,
      "type": "water"
    },
    {
      "id": 478021084,
      "lat": 11.4685895,
      "lon": 76.2289303,
      "type": "water"
    },
    {
      "id": 478021085,
      "lat": 11.4747173,
      "lon": 76.2286782,
      "type": "water"
    },
    {
      "id": 478021086,
      "lat": 11.4809565,
      "lon": 76.2298572,
      "type": "water"
    },
    {
      "id": 478021551,
      "lat": 11.4870283,
      "lon": 76.2285644,
      "type": "water"
    },
    {
      "id": 478021552,
      "lat": 11.4930281,
      "lon": 76.2285725,
      "type": "water"
    },
    {
      "id": 478021553,
      "lat": 11.4990677,
      "lon": 76.2287677,
      "type": "water"
    },
    {
      "id": 478021554,
      "lat": 11.5053462,
      "lon": 76.2273448,
      "type": "water"
    },
    {
      "id": 478021555,
      "lat": 11.5102354,
      "lon": 76.2213523,
      "type": "water"
    },
    {
      "id": 478021556,
      "lat": 11.509816,
      "lon": 76.2134327,
      "type": "water"
    },
    {
      "id": 478021557,
      "lat": 11.5082145,
      "lon": 76.2055295,
      "type": "water"
    },
    {
      "id": 478021558,
      "lat": 11.506637,
      "lon": 76.1973335,
      "type": "water"
    },
    {
      "id": 484312073,
      "lat": 11.6299267,
      "lon": 76.0667229,
      "type": "religious"
    },
    {
      "id": 485874633,
      "lat": 11.5778549,
      "lon": 76.052998,
      "type": "industrial"
    },
    {
      "id": 552795594,
      "lat": 11.6001336,
      "lon": 76.1723214,
      "type": "water"
    },
    {
      "id": 583222154,
      "lat": 11.6244079,
      "lon": 76.1266306,
      "type": "quarry"
    },
    {
      "id": 720616389,
      "lat": 11.4571988,
      "lon": 76.2410791,
      "type": "residential"
    },
    {
      "id": 736440454,
      "lat": 11.4822951,
      "lon": 76.1528051,
      "type": "water"
    },
    {
      "id": 762820946,
      "lat": 11.5235522,
      "lon": 76.1528461,
      "type": "water"
    },
    {
      "id": 762825691,
      "lat": 11.5351257,
      "lon": 76.1747122,
      "type": "recreation_ground"
    },
    {
      "id": 785570998,
      "lat": 11.4964605,
      "lon": 76.1432683,
      "type": "orchard"
    },
    {
      "id": 785570999,
      "lat": 11.490812,
      "lon": 76.14896,
      "type": "orchard"
    },
    {
      "id": 785571000,
      "lat": 11.539421,
      "lon": 76.15978,
      "type": "residential"
    },
    {
      "id": 794754885,
      "lat": 11.6482324,
      "lon": 76.1051233,
      "type": "water"
    },
    {
      "id": 794754886,
      "lat": 11.6455516,
      "lon": 76.1069963,
      "type": "water"
    },
    {
      "id": 794754887,
      "lat": 11.6464758,
      "lon": 76.1068308,
      "type": "water"
    },
    {
      "id": 794754888,
      "lat": 11.6468857,
      "lon": 76.1049184,
      "type": "water"
    },
    {
      "id": 794754889,
      "lat": 11.6456693,
      "lon": 76.1054334,
      "type": "water"
    },
    {
      "id": 794754890,
      "lat": 11.6449968,
      "lon": 76.1080345,
      "type": "water"
    },
    {
      "id": 794754891,
      "lat": 11.6455184,
      "lon": 76.1079597,
      "type": "water"
    },
    {
      "id": 794754894,
      "lat": 11.6124438,
      "lon": 76.1311252,
      "type": "water"
    },
    {
      "id": 794754901,
      "lat": 11.6312741,
      "lon": 76.1046413,
      "type": "water"
    },
    {
      "id": 794863116,
      "lat": 11.5789652,
      "lon": 76.1388976,
      "type": "water"
    },
    {
      "id": 794865670,
      "lat": 11.5806771,
      "lon": 76.1202717,
      "type": "water"
    },
    {
      "id": 794899786,
      "lat": 11.5828443,
      "lon": 76.1342972,
      "type": "water"
    },
    {
      "id": 794899787,
      "lat": 11.5743266,
      "lon": 76.1140628,
      "type": "water"
    },
    {
      "id": 794899788,
      "lat": 11.5816935,
      "lon": 76.1150865,
      "type": "water"
    },
    {
      "id": 794899789,
      "lat": 11.5807512,
      "lon": 76.1164844,
      "type": "water"
    },
    {
      "id": 794899790,
      "lat": 11.5833908,
      "lon": 76.1148029,
      "type": "water"
    },
    {
      "id": 794899791,
      "lat": 11.5866264,
      "lon": 76.1023723,
      "type": "water"
    },
    {
      "id": 794899792,
      "lat": 11.5850932,
      "lon": 76.1017354,
      "type": "water"
    },
    {
      "id": 794899793,
      "lat": 11.5849763,
      "lon": 76.1015946,
      "type": "water"
    },
    {
      "id": 794899794,
      "lat": 11.5850907,
      "lon": 76.1015275,
      "type": "water"
    },
    {
      "id": 794899795,
      "lat": 11.5850696,
      "lon": 76.1015986,
      "type": "water"
    },
    {
      "id": 794899796,
      "lat": 11.5851616,
      "lon": 76.1015825,
      "type": "water"
    },
    {
      "id": 794899797,
      "lat": 11.5849461,
      "lon": 76.1018159,
      "type": "water"
    },
    {
      "id": 794899798,
      "lat": 11.5796882,
      "lon": 76.1220772,
      "type": "water"
    },
    {
      "id": 794899799,
      "lat": 11.606733,
      "lon": 76.1369662,
      "type": "water"
    },
    {
      "id": 794899800,
      "lat": 11.5968015,
      "lon": 76.1399622,
      "type": "water"
    },
    {
      "id": 794899801,
      "lat": 11.5969301,
      "lon": 76.1397262,
      "type": "water"
    },
    {
      "id": 794899802,
      "lat": 11.5969538,
      "lon": 76.1398227,
      "type": "water"
    },
    {
      "id": 794910214,
      "lat": 11.5368396,
      "lon": 76.1175046,
      "type": "water"
    },
    {
      "id": 794915295,
      "lat": 11.5379236,
      "lon": 76.1362692,
      "type": "quarry"
    },
    {
      "id": 794915296,
      "lat": 11.538662,
      "lon": 76.1412045,
      "type": "water"
    },
    {
      "id": 794915297,
      "lat": 11.5460243,
      "lon": 76.1455657,
      "type": "water"
    },
    {
      "id": 794915298,
      "lat": 11.536423,
      "lon": 76.1425589,
      "type": "water"
    },
    {
      "id": 794915299,
      "lat": 11.5228068,
      "lon": 76.128429,
      "type": "water"
    },
    {
      "id": 794915300,
      "lat": 11.5221984,
      "lon": 76.1161765,
      "type": "water"
    },
    {
      "id": 795117558,
      "lat": 11.4799905,
      "lon": 76.1455003,
      "type": "water"
    },
    {
      "id": 795117559,
      "lat": 11.4776926,
      "lon": 76.1452292,
      "type": "water"
    },
    {
      "id": 795277550,
      "lat": 11.6476864,
      "lon": 76.104842,
      "type": "water"
    },
    {
      "id": 795277551,
      "lat": 11.6468722,
      "lon": 76.1049005,
      "type": "water"
    },
    {
      "id": 795277553,
      "lat": 11.6476868,
      "lon": 76.0610062,
      "type": "water"
    },
    {
      "id": 795277554,
      "lat": 11.6470651,
      "lon": 76.0679931,
      "type": "water"
    },
    {
      "id": 795277555,
      "lat": 11.645507,
      "lon": 76.0695928,
      "type": "water"
    },
    {
      "id": 795277556,
      "lat": 11.6430486,
      "lon": 76.0679733,
      "type": "water"
    },
    {
      "id": 795277557,
      "lat": 11.6349488,
      "lon": 76.068976,
      "type": "water"
    },
    {
      "id": 795277559,
      "lat": 11.6255274,
      "lon": 76.0791192,
      "type": "water"
    },
    {
      "id": 795552921,
      "lat": 11.6244922,
      "lon": 76.2411463,
      "type": "water"
    },
    {
      "id": 795623244,
      "lat": 11.646997,
      "lon": 76.1891023,
      "type": "water"
    },
    {
      "id": 795623245,
      "lat": 11.6469733,
      "lon": 76.18929,
      "type": "water"
    },
    {
      "id": 795623246,
      "lat": 11.6467002,
      "lon": 76.1893061,
      "type": "water"
    },
    {
      "id": 795623247,
      "lat": 11.6408603,
      "lon": 76.1828393,
      "type": "water"
    },
    {
      "id": 795623248,
      "lat": 11.6382306,
      "lon": 76.1745888,
      "type": "water"
    },
    {
      "id": 795623255,
      "lat": 11.6296951,
      "lon": 76.1687845,
      "type": "water"
    },
    {
      "id": 795623258,
      "lat": 11.611382,
      "lon": 76.1514441,
      "type": "water"
    },
    {
      "id": 795623260,
      "lat": 11.6119436,
      "lon": 76.1880448,
      "type": "water"
    },
    {
      "id": 795623262,
      "lat": 11.6411309,
      "lon": 76.1780503,
      "type": "water"
    },
    {
      "id": 795921801,
      "lat": 11.649414,
      "lon": 76.193435,
      "type": "water"
    },
    {
      "id": 795921802,
      "lat": 11.6378921,
      "lon": 76.1983175,
      "type": "water"
    },
    {
      "id": 795921803,
      "lat": 11.6241957,
      "lon": 76.2232519,
      "type": "water"
    },
    {
      "id": 795935037,
      "lat": 11.6058157,
      "lon": 76.191543,
      "type": "water"
    },
    {
      "id": 795935038,
      "lat": 11.6046118,
      "lon": 76.1978122,
      "type": "water"
    },
    {
      "id": 795935039,
      "lat": 11.6041703,
      "lon": 76.2004547,
      "type": "water"
    },
    {
      "id": 795935040,
      "lat": 11.6066494,
      "lon": 76.2063759,
      "type": "water"
    },
    {
      "id": 795935042,
      "lat": 11.6063322,
      "lon": 76.2114114,
      "type": "water"
    },
    {
      "id": 795935045,
      "lat": 11.6052751,
      "lon": 76.2349553,
      "type": "water"
    },
    {
      "id": 795935046,
      "lat": 11.6133128,
      "lon": 76.2326598,
      "type": "water"
    },
    {
      "id": 795935047,
      "lat": 11.6138831,
      "lon": 76.225812,
      "type": "water"
    },
    {
      "id": 795935048,
      "lat": 11.6159266,
      "lon": 76.2269065,
      "type": "water"
    },
    {
      "id": 796368845,
      "lat": 11.5382762,
      "lon": 76.2212273,
      "type": "water"
    },
    {
      "id": 796368846,
      "lat": 11.5659716,
      "lon": 76.2363927,
      "type": "water"
    },
    {
      "id": 796368849,
      "lat": 11.5576863,
      "lon": 76.1983642,
      "type": "water"
    },
    {
      "id": 796368852,
      "lat": 11.5628507,
      "lon": 76.2052706,
      "type": "water"
    },
    {
      "id": 796478300,
      "lat": 11.5962743,
      "lon": 76.0522054,
      "type": "water"
    },
    {
      "id": 796478301,
      "lat": 11.6075854,
      "lon": 76.0655379,
      "type": "water"
    },
    {
      "id": 796478302,
      "lat": 11.6074629,
      "lon": 76.0655258,
      "type": "water"
    },
    {
      "id": 796478303,
      "lat": 11.6086103,
      "lon": 76.06514,
      "type": "water"
    },
    {
      "id": 796478304,
      "lat": 11.6088026,
      "lon": 76.0649853,
      "type": "water"
    },
    {
      "id": 796478306,
      "lat": 11.5878517,
      "lon": 76.0530617,
      "type": "water"
    },
    {
      "id": 796478307,
      "lat": 11.5870474,
      "lon": 76.0630623,
      "type": "water"
    },
    {
      "id": 796478308,
      "lat": 11.5915259,
      "lon": 76.0773961,
      "type": "water"
    },
    {
      "id": 796478309,
      "lat": 11.5723455,
      "lon": 76.086996,
      "type": "water"
    },
    {
      "id": 796478311,
      "lat": 11.5689832,
      "lon": 76.0522489,
      "type": "water"
    },
    {
      "id": 796478312,
      "lat": 11.5691017,
      "lon": 76.0526582,
      "type": "water"
    },
    {
      "id": 796478313,
      "lat": 11.5695443,
      "lon": 76.0511714,
      "type": "water"
    },
    {
      "id": 796478314,
      "lat": 11.6336423,
      "lon": 76.087903,
      "type": "water"
    },
    {
      "id": 796478315,
      "lat": 11.6327339,
      "lon": 76.0861247,
      "type": "water"
    },
    {
      "id": 796478316,
      "lat": 11.6271939,
      "lon": 76.0911425,
      "type": "water"
    },
    {
      "id": 796478317,
      "lat": 11.6245,
      "lon": 76.0889069,
      "type": "water"
    },
    {
      "id": 796729619,
      "lat": 11.5215437,
      "lon": 76.1898631,
      "type": "water"
    },
    {
      "id": 796729623,
      "lat": 11.519343,
      "lon": 76.2221928,
      "type": "water"
    },
    {
      "id": 797053017,
      "lat": 11.566803,
      "lon": 76.0610855,
      "type": "water"
    },
    {
      "id": 797053022,
      "lat": 11.5667075,
      "lon": 76.082996,
      "type": "water"
    },
    {
      "id": 797053023,
      "lat": 11.5669256,
      "lon": 76.0831193,
      "type": "water"
    },
    {
      "id": 797053032,
      "lat": 11.5202676,
      "lon": 76.0905921,
      "type": "water"
    },
    {
      "id": 797814211,
      "lat": 11.6029637,
      "lon": 76.0509534,
      "type": "water"
    },
    {
      "id": 797909317,
      "lat": 11.631585,
      "lon": 76.2354946,
      "type": "water"
    },
    {
      "id": 797909318,
      "lat": 11.6472001,
      "lon": 76.2469878,
      "type": "water"
    },
    {
      "id": 797973672,
      "lat": 11.5902593,
      "lon": 76.2424343,
      "type": "water"
    },
    {
      "id": 797973674,
      "lat": 11.6078009,
      "lon": 76.2413244,
      "type": "water"
    },
    {
      "id": 797973693,
      "lat": 11.5908091,
      "lon": 76.247917,
      "type": "water"
    },
    {
      "id": 797973697,
      "lat": 11.5824932,
      "lon": 76.2470622,
      "type": "water"
    },
    {
      "id": 797973705,
      "lat": 11.5922736,
      "lon": 76.2366002,
      "type": "water"
    },
    {
      "id": 799045185,
      "lat": 11.6175295,
      "lon": 76.2091975,
      "type": "water"
    },
    {
      "id": 799059576,
      "lat": 11.6156675,
      "lon": 76.2125866,
      "type": "water"
    },
    {
      "id": 799059577,
      "lat": 11.6161912,
      "lon": 76.2124654,
      "type": "water"
    },
    {
      "id": 799059578,
      "lat": 11.6165618,
      "lon": 76.2120732,
      "type": "water"
    },
    {
      "id": 799718367,
      "lat": 11.4701242,
      "lon": 76.0506606,
      "type": "water"
    },
    {
      "id": 799719287,
      "lat": 11.4693749,
      "lon": 76.0508491,
      "type": "water"
    },
    {
      "id": 800107079,
      "lat": 11.6113355,
      "lon": 76.2096104,
      "type": "water"
    },
    {
      "id": 800597884,
      "lat": 11.529306,
      "lon": 76.1659375,
      "type": "water"
    },
    {
      "id": 803206717,
      "lat": 11.6283961,
      "lon": 76.053438,
      "type": "farmland"
    },
    {
      "id": 803206732,
      "lat": 11.6295783,
      "lon": 76.0542454,
      "type": "farmland"
    },
    {
      "id": 803206737,
      "lat": 11.6298229,
      "lon": 76.0546719,
      "type": "farmland"
    },
    {
      "id": 803206738,
      "lat": 11.6305506,
      "lon": 76.0554578,
      "type": "farmland"
    },
    {
      "id": 803228905,
      "lat": 11.5971379,
      "lon": 76.0645324,
      "type": "farmland"
    },
    {
      "id": 803228907,
      "lat": 11.5968687,
      "lon": 76.0805026,
      "type": "farmland"
    },
    {
      "id": 803228908,
      "lat": 11.583482,
      "lon": 76.0668892,
      "type": "farmland"
    },
    {
      "id": 803228909,
      "lat": 11.5946081,
      "lon": 76.0794971,
      "type": "farmland"
    },
    {
      "id": 803228913,
      "lat": 11.5941898,
      "lon": 76.0693806,
      "type": "farmland"
    },
    {
      "id": 803228915,
      "lat": 11.5966685,
      "lon": 76.0705449,
      "type": "farmland"
    },
    {
      "id": 803228919,
      "lat": 11.5974179,
      "lon": 76.0696133,
      "type": "farmland"
    },
    {
      "id": 803228920,
      "lat": 11.5952784,
      "lon": 76.069368,
      "type": "farmland"
    },
    {
      "id": 803569220,
      "lat": 11.6453661,
      "lon": 76.1379003,
      "type": "farmland"
    },
    {
      "id": 803569221,
      "lat": 11.6459259,
      "lon": 76.1370388,
      "type": "farmland"
    },
    {
      "id": 803569222,
      "lat": 11.6452508,
      "lon": 76.1373369,
      "type": "farmland"
    },
    {
      "id": 803569223,
      "lat": 11.6451671,
      "lon": 76.1368099,
      "type": "farmland"
    },
    {
      "id": 803569224,
      "lat": 11.6447827,
      "lon": 76.1362331,
      "type": "farmland"
    },
    {
      "id": 803569228,
      "lat": 11.6443731,
      "lon": 76.139376,
      "type": "farmland"
    },
    {
      "id": 803569230,
      "lat": 11.6458701,
      "lon": 76.1366238,
      "type": "farmland"
    },
    {
      "id": 803569231,
      "lat": 11.6443431,
      "lon": 76.1402769,
      "type": "farmland"
    },
    {
      "id": 803569233,
      "lat": 11.6443462,
      "lon": 76.1359383,
      "type": "farmland"
    },
    {
      "id": 803573969,
      "lat": 11.6482228,
      "lon": 76.1412795,
      "type": "farmland"
    },
    {
      "id": 803573970,
      "lat": 11.6484759,
      "lon": 76.1415429,
      "type": "farmland"
    },
    {
      "id": 803573972,
      "lat": 11.6492253,
      "lon": 76.1408777,
      "type": "farmland"
    },
    {
      "id": 803573973,
      "lat": 11.648551,
      "lon": 76.1405343,
      "type": "farmland"
    },
    {
      "id": 803573974,
      "lat": 11.6486339,
      "lon": 76.1417411,
      "type": "farmland"
    },
    {
      "id": 803573975,
      "lat": 11.6489165,
      "lon": 76.1411412,
      "type": "farmland"
    },
    {
      "id": 803573981,
      "lat": 11.6486892,
      "lon": 76.1413456,
      "type": "farmland"
    },
    {
      "id": 803573982,
      "lat": 11.6488144,
      "lon": 76.1414701,
      "type": "farmland"
    },
    {
      "id": 803573983,
      "lat": 11.6494027,
      "lon": 76.1411595,
      "type": "farmland"
    },
    {
      "id": 803573984,
      "lat": 11.6478321,
      "lon": 76.1392632,
      "type": "farmland"
    },
    {
      "id": 803573986,
      "lat": 11.6478594,
      "lon": 76.1411588,
      "type": "farmland"
    },
    {
      "id": 803573987,
      "lat": 11.6488119,
      "lon": 76.1419304,
      "type": "farmland"
    },
    {
      "id": 803587472,
      "lat": 11.5971844,
      "lon": 76.0814123,
      "type": "recreation_ground"
    },
    {
      "id": 803603360,
      "lat": 11.6340261,
      "lon": 76.0596392,
      "type": "farmland"
    },
    {
      "id": 803663060,
      "lat": 11.6218499,
      "lon": 76.2084585,
      "type": "water"
    },
    {
      "id": 803663061,
      "lat": 11.6217769,
      "lon": 76.2082967,
      "type": "quarry"
    },
    {
      "id": 803663062,
      "lat": 11.6244003,
      "lon": 76.2124562,
      "type": "farmland"
    },
    {
      "id": 803667002,
      "lat": 11.6129353,
      "lon": 76.2134117,
      "type": "farmland"
    },
    {
      "id": 803674161,
      "lat": 11.6451195,
      "lon": 76.1484946,
      "type": "farmland"
    },
    {
      "id": 803674162,
      "lat": 11.6439823,
      "lon": 76.1438145,
      "type": "farmland"
    },
    {
      "id": 803674163,
      "lat": 11.6451109,
      "lon": 76.1482695,
      "type": "farmland"
    },
    {
      "id": 803674164,
      "lat": 11.6420952,
      "lon": 76.1431379,
      "type": "farmland"
    },
    {
      "id": 803674165,
      "lat": 11.6435421,
      "lon": 76.1438141,
      "type": "farmland"
    },
    {
      "id": 803674167,
      "lat": 11.6446277,
      "lon": 76.14375,
      "type": "farmland"
    },
    {
      "id": 803680111,
      "lat": 11.6361676,
      "lon": 76.1433588,
      "type": "farmland"
    },
    {
      "id": 803707815,
      "lat": 11.6480563,
      "lon": 76.1372372,
      "type": "farmland"
    },
    {
      "id": 803707820,
      "lat": 11.64855,
      "lon": 76.1376789,
      "type": "farmland"
    },
    {
      "id": 803711259,
      "lat": 11.6497615,
      "lon": 76.1384167,
      "type": "farmland"
    },
    {
      "id": 803738912,
      "lat": 11.6324999,
      "lon": 76.056596,
      "type": "farmland"
    },
    {
      "id": 803738926,
      "lat": 11.6340246,
      "lon": 76.0512477,
      "type": "water"
    },
    {
      "id": 803738928,
      "lat": 11.6358688,
      "lon": 76.0517439,
      "type": "water"
    },
    {
      "id": 803738934,
      "lat": 11.6392552,
      "lon": 76.0554493,
      "type": "farmland"
    },
    {
      "id": 803738935,
      "lat": 11.6406082,
      "lon": 76.055672,
      "type": "farmland"
    },
    {
      "id": 803738936,
      "lat": 11.6419505,
      "lon": 76.0547627,
      "type": "farmland"
    },
    {
      "id": 803748612,
      "lat": 11.6406495,
      "lon": 76.1015766,
      "type": "water"
    },
    {
      "id": 803748613,
      "lat": 11.6396662,
      "lon": 76.0961994,
      "type": "water"
    },
    {
      "id": 803748614,
      "lat": 11.6335507,
      "lon": 76.1058772,
      "type": "water"
    },
    {
      "id": 803748618,
      "lat": 11.639708,
      "lon": 76.1016945,
      "type": "water"
    },
    {
      "id": 803754171,
      "lat": 11.6093171,
      "lon": 76.0782824,
      "type": "recreation_ground"
    },
    {
      "id": 803796906,
      "lat": 11.6282006,
      "lon": 76.2280294,
      "type": "water"
    },
    {
      "id": 803800120,
      "lat": 11.6204731,
      "lon": 76.2408512,
      "type": "water"
    },
    {
      "id": 803800121,
      "lat": 11.6215515,
      "lon": 76.243288,
      "type": "recreation_ground"
    },
    {
      "id": 804081717,
      "lat": 11.6296915,
      "lon": 76.0739294,
      "type": "farmland"
    },
    {
      "id": 804081718,
      "lat": 11.6301985,
      "lon": 76.071376,
      "type": "farmland"
    },
    {
      "id": 804081736,
      "lat": 11.619054,
      "lon": 76.0544555,
      "type": "farmland"
    },
    {
      "id": 804081737,
      "lat": 11.6165423,
      "lon": 76.0546111,
      "type": "farmland"
    },
    {
      "id": 804198581,
      "lat": 11.6490685,
      "lon": 76.1455234,
      "type": "farmland"
    },
    {
      "id": 804198591,
      "lat": 11.6489925,
      "lon": 76.1458301,
      "type": "farmland"
    },
    {
      "id": 804207201,
      "lat": 11.6448943,
      "lon": 76.1510754,
      "type": "farmland"
    },
    {
      "id": 804207207,
      "lat": 11.6444931,
      "lon": 76.1507912,
      "type": "farmland"
    },
    {
      "id": 804207209,
      "lat": 11.6455653,
      "lon": 76.1502255,
      "type": "farmland"
    },
    {
      "id": 804211105,
      "lat": 11.648418,
      "lon": 76.1552057,
      "type": "farmland"
    },
    {
      "id": 804211107,
      "lat": 11.6484991,
      "lon": 76.1547772,
      "type": "farmland"
    },
    {
      "id": 804211108,
      "lat": 11.6506562,
      "lon": 76.1559319,
      "type": "farmland"
    },
    {
      "id": 804211109,
      "lat": 11.64857,
      "lon": 76.1570773,
      "type": "farmland"
    },
    {
      "id": 804211111,
      "lat": 11.64731,
      "lon": 76.1558273,
      "type": "farmland"
    },
    {
      "id": 804211112,
      "lat": 11.6459839,
      "lon": 76.1565669,
      "type": "farmland"
    },
    {
      "id": 804229697,
      "lat": 11.6485998,
      "lon": 76.1276632,
      "type": "farmland"
    },
    {
      "id": 804229698,
      "lat": 11.6473607,
      "lon": 76.1217656,
      "type": "farmland"
    },
    {
      "id": 804294403,
      "lat": 11.6427866,
      "lon": 76.1532392,
      "type": "farmland"
    },
    {
      "id": 804294407,
      "lat": 11.6422579,
      "lon": 76.1538097,
      "type": "farmland"
    },
    {
      "id": 804294408,
      "lat": 11.6443655,
      "lon": 76.1556175,
      "type": "farmland"
    },
    {
      "id": 804294409,
      "lat": 11.6438418,
      "lon": 76.155142,
      "type": "farmland"
    },
    {
      "id": 804294413,
      "lat": 11.6431258,
      "lon": 76.1533845,
      "type": "farmland"
    },
    {
      "id": 804294415,
      "lat": 11.6431106,
      "lon": 76.1543426,
      "type": "farmland"
    },
    {
      "id": 804297887,
      "lat": 11.6333398,
      "lon": 76.139476,
      "type": "farmland"
    },
    {
      "id": 804297894,
      "lat": 11.6336244,
      "lon": 76.1388544,
      "type": "farmland"
    },
    {
      "id": 804529450,
      "lat": 11.5983912,
      "lon": 76.0515827,
      "type": "farmland"
    },
    {
      "id": 804568276,
      "lat": 11.6087158,
      "lon": 76.1443262,
      "type": "farmland"
    },
    {
      "id": 804568278,
      "lat": 11.6092401,
      "lon": 76.1437002,
      "type": "water"
    },
    {
      "id": 804568279,
      "lat": 11.6094293,
      "lon": 76.1438321,
      "type": "water"
    },
    {
      "id": 804568281,
      "lat": 11.6114229,
      "lon": 76.144602,
      "type": "farmland"
    },
    {
      "id": 804569571,
      "lat": 11.612047,
      "lon": 76.145776,
      "type": "farmland"
    },
    {
      "id": 804569572,
      "lat": 11.612633,
      "lon": 76.1490124,
      "type": "farmland"
    },
    {
      "id": 804569574,
      "lat": 11.6144798,
      "lon": 76.1455964,
      "type": "farmland"
    },
    {
      "id": 804569874,
      "lat": 11.6187159,
      "lon": 76.1509626,
      "type": "farmland"
    },
    {
      "id": 804788659,
      "lat": 11.6198608,
      "lon": 76.0782961,
      "type": "residential"
    },
    {
      "id": 804882179,
      "lat": 11.6073922,
      "lon": 76.0488036,
      "type": "farmland"
    },
    {
      "id": 805391806,
      "lat": 11.6414061,
      "lon": 76.0503579,
      "type": "farmland"
    },
    {
      "id": 805391807,
      "lat": 11.6422155,
      "lon": 76.051586,
      "type": "farmland"
    },
    {
      "id": 805391808,
      "lat": 11.6392929,
      "lon": 76.0641026,
      "type": "farmland"
    },
    {
      "id": 806111459,
      "lat": 11.6203456,
      "lon": 76.0905431,
      "type": "water"
    },
    {
      "id": 806111460,
      "lat": 11.6189232,
      "lon": 76.0898801,
      "type": "water"
    },
    {
      "id": 806699860,
      "lat": 11.6480705,
      "lon": 76.1367713,
      "type": "farmland"
    },
    {
      "id": 806699867,
      "lat": 11.648172,
      "lon": 76.1363645,
      "type": "farmland"
    },
    {
      "id": 806789771,
      "lat": 11.643973,
      "lon": 76.1516429,
      "type": "farmland"
    },
    {
      "id": 806790987,
      "lat": 11.6473182,
      "lon": 76.11516,
      "type": "farmland"
    },
    {
      "id": 806790988,
      "lat": 11.6482633,
      "lon": 76.1144351,
      "type": "farmland"
    },
    {
      "id": 806790990,
      "lat": 11.6487131,
      "lon": 76.1160976,
      "type": "farmland"
    },
    {
      "id": 824057277,
      "lat": 11.6126063,
      "lon": 76.1413934,
      "type": "farmland"
    },
    {
      "id": 824057278,
      "lat": 11.6106752,
      "lon": 76.1390278,
      "type": "farmland"
    },
    {
      "id": 824057279,
      "lat": 11.6076275,
      "lon": 76.1371301,
      "type": "farmland"
    },
    {
      "id": 824057280,
      "lat": 11.6030177,
      "lon": 76.1414941,
      "type": "farmland"
    },
    {
      "id": 824057281,
      "lat": 11.6006807,
      "lon": 76.1454796,
      "type": "farmland"
    },
    {
      "id": 824074884,
      "lat": 11.6371391,
      "lon": 76.156367,
      "type": "farmland"
    },
    {
      "id": 824074885,
      "lat": 11.6429106,
      "lon": 76.1759095,
      "type": "farmland"
    },
    {
      "id": 824074886,
      "lat": 11.6387783,
      "lon": 76.167883,
      "type": "farmland"
    },
    {
      "id": 824074888,
      "lat": 11.6406409,
      "lon": 76.1652115,
      "type": "farmland"
    },
    {
      "id": 824074889,
      "lat": 11.6380244,
      "lon": 76.1629303,
      "type": "farmland"
    },
    {
      "id": 824074890,
      "lat": 11.6375699,
      "lon": 76.1603406,
      "type": "farmland"
    },
    {
      "id": 824074891,
      "lat": 11.6406593,
      "lon": 76.1577161,
      "type": "farmland"
    },
    {
      "id": 824074892,
      "lat": 11.6379612,
      "lon": 76.1555609,
      "type": "farmland"
    },
    {
      "id": 824659060,
      "lat": 11.6450477,
      "lon": 76.1614531,
      "type": "farmland"
    },
    {
      "id": 824659062,
      "lat": 11.6485584,
      "lon": 76.1607504,
      "type": "farmland"
    },
    {
      "id": 831278381,
      "lat": 11.5740161,
      "lon": 76.141718,
      "type": "orchard"
    },
    {
      "id": 831296453,
      "lat": 11.6179894,
      "lon": 76.2540811,
      "type": "orchard"
    },
    {
      "id": 831296454,
      "lat": 11.6249883,
      "lon": 76.2618112,
      "type": "forest"
    },
    {
      "id": 831296461,
      "lat": 11.6219199,
      "lon": 76.213569,
      "type": "recreation_ground"
    },
    {
      "id": 831296462,
      "lat": 11.6508533,
      "lon": 76.2176326,
      "type": "residential"
    },
    {
      "id": 831296463,
      "lat": 11.6416443,
      "lon": 76.223461,
      "type": "orchard"
    },
    {
      "id": 831296464,
      "lat": 11.6315719,
      "lon": 76.2338143,
      "type": "forest"
    },
    {
      "id": 836066948,
      "lat": 11.5738824,
      "lon": 76.0691567,
      "type": "recreation_ground"
    },
    {
      "id": 839429000,
      "lat": 11.5741858,
      "lon": 76.0558673,
      "type": "recreation_ground"
    },
    {
      "id": 839466345,
      "lat": 11.6142061,
      "lon": 76.0873241,
      "type": "recreation_ground"
    },
    {
      "id": 839468867,
      "lat": 11.6119717,
      "lon": 76.0824021,
      "type": "recreation_ground"
    },
    {
      "id": 839475630,
      "lat": 11.5715043,
      "lon": 76.1092479,
      "type": "recreation_ground"
    },
    {
      "id": 839481206,
      "lat": 11.551671,
      "lon": 76.1065524,
      "type": "recreation_ground"
    },
    {
      "id": 839598745,
      "lat": 11.4982663,
      "lon": 76.1600707,
      "type": "recreation_ground"
    },
    {
      "id": 839603071,
      "lat": 11.5453537,
      "lon": 76.181411,
      "type": "recreation_ground"
    },
    {
      "id": 839723356,
      "lat": 11.5960962,
      "lon": 76.1821253,
      "type": "recreation_ground"
    },
    {
      "id": 839742130,
      "lat": 11.56354,
      "lon": 76.2002342,
      "type": "recreation_ground"
    },
    {
      "id": 839749158,
      "lat": 11.5591986,
      "lon": 76.222728,
      "type": "recreation_ground"
    },
    {
      "id": 839755914,
      "lat": 11.6177433,
      "lon": 76.2012722,
      "type": "recreation_ground"
    },
    {
      "id": 839858297,
      "lat": 11.6006786,
      "lon": 76.2279543,
      "type": "recreation_ground"
    },
    {
      "id": 839885503,
      "lat": 11.5308677,
      "lon": 76.1355865,
      "type": "recreation_ground"
    },
    {
      "id": 847155602,
      "lat": 11.5407376,
      "lon": 76.147136,
      "type": "water"
    },
    {
      "id": 847197656,
      "lat": 11.6485627,
      "lon": 76.0641067,
      "type": "water"
    },
    {
      "id": 847197812,
      "lat": 11.6458402,
      "lon": 76.0717766,
      "type": "water"
    },
    {
      "id": 847214632,
      "lat": 11.643144,
      "lon": 76.0854586,
      "type": "water"
    },
    {
      "id": 848392139,
      "lat": 11.6318236,
      "lon": 76.1864363,
      "type": "water"
    },
    {
      "id": 848392268,
      "lat": 11.6319896,
      "lon": 76.1895756,
      "type": "water"
    },
    {
      "id": 848393858,
      "lat": 11.6321913,
      "lon": 76.1901035,
      "type": "water"
    },
    {
      "id": 848394242,
      "lat": 11.6296903,
      "lon": 76.1830632,
      "type": "water"
    },
    {
      "id": 858387936,
      "lat": 11.5393748,
      "lon": 76.2312748,
      "type": "water"
    },
    {
      "id": 858387942,
      "lat": 11.5393556,
      "lon": 76.2312225,
      "type": "water"
    },
    {
      "id": 877402190,
      "lat": 11.6430888,
      "lon": 76.2310447,
      "type": "water"
    },
    {
      "id": 877402191,
      "lat": 11.6308074,
      "lon": 76.221129,
      "type": "water"
    },
    {
      "id": 877402776,
      "lat": 11.6246019,
      "lon": 76.2181276,
      "type": "water"
    },
    {
      "id": 877403394,
      "lat": 11.6189488,
      "lon": 76.220678,
      "type": "water"
    },
    {
      "id": 877403395,
      "lat": 11.6194982,
      "lon": 76.2227635,
      "type": "water"
    },
    {
      "id": 877403396,
      "lat": 11.6184479,
      "lon": 76.2237567,
      "type": "water"
    },
    {
      "id": 877403397,
      "lat": 11.6165632,
      "lon": 76.2229366,
      "type": "water"
    },
    {
      "id": 877404086,
      "lat": 11.6156012,
      "lon": 76.2148795,
      "type": "water"
    },
    {
      "id": 877404087,
      "lat": 11.6131613,
      "lon": 76.2169956,
      "type": "water"
    },
    {
      "id": 877404088,
      "lat": 11.6122682,
      "lon": 76.2182472,
      "type": "water"
    },
    {
      "id": 877405242,
      "lat": 11.6028043,
      "lon": 76.2286263,
      "type": "water"
    },
    {
      "id": 877406450,
      "lat": 11.6082229,
      "lon": 76.2444804,
      "type": "water"
    },
    {
      "id": 877406451,
      "lat": 11.602115,
      "lon": 76.2429058,
      "type": "water"
    },
    {
      "id": 877406452,
      "lat": 11.6005685,
      "lon": 76.2423747,
      "type": "water"
    },
    {
      "id": 877406453,
      "lat": 11.6013841,
      "lon": 76.2394102,
      "type": "water"
    },
    {
      "id": 882276404,
      "lat": 11.6295788,
      "lon": 76.2102855,
      "type": "water"
    },
    {
      "id": 882276405,
      "lat": 11.623615,
      "lon": 76.2146374,
      "type": "water"
    },
    {
      "id": 882276406,
      "lat": 11.6200715,
      "lon": 76.213381,
      "type": "water"
    },
    {
      "id": 882276407,
      "lat": 11.6136803,
      "lon": 76.2061378,
      "type": "water"
    },
    {
      "id": 882276408,
      "lat": 11.6151563,
      "lon": 76.2079514,
      "type": "water"
    },
    {
      "id": 882276409,
      "lat": 11.6143636,
      "lon": 76.2090556,
      "type": "water"
    },
    {
      "id": 882276410,
      "lat": 11.613989,
      "lon": 76.2093994,
      "type": "water"
    },
    {
      "id": 882276411,
      "lat": 11.6138878,
      "lon": 76.2109444,
      "type": "water"
    },
    {
      "id": 882277267,
      "lat": 11.6065321,
      "lon": 76.2172934,
      "type": "water"
    },
    {
      "id": 886862089,
      "lat": 11.5921856,
      "lon": 76.0506721,
      "type": "water"
    },
    {
      "id": 886862090,
      "lat": 11.591354,
      "lon": 76.0532377,
      "type": "water"
    },
    {
      "id": 886862091,
      "lat": 11.5940146,
      "lon": 76.0526318,
      "type": "water"
    },
    {
      "id": 886862092,
      "lat": 11.59211,
      "lon": 76.0678271,
      "type": "water"
    },
    {
      "id": 886862093,
      "lat": 11.5926326,
      "lon": 76.0681081,
      "type": "water"
    },
    {
      "id": 886862094,
      "lat": 11.5974302,
      "lon": 76.0650861,
      "type": "water"
    },
    {
      "id": 886862095,
      "lat": 11.5975564,
      "lon": 76.0653825,
      "type": "water"
    },
    {
      "id": 886862096,
      "lat": 11.5977593,
      "lon": 76.0653174,
      "type": "water"
    },
    {
      "id": 886862714,
      "lat": 11.643229,
      "lon": 76.1978453,
      "type": "water"
    },
    {
      "id": 886862715,
      "lat": 11.6395801,
      "lon": 76.200564,
      "type": "water"
    },
    {
      "id": 886862716,
      "lat": 11.6398826,
      "lon": 76.2004566,
      "type": "water"
    },
    {
      "id": 886863407,
      "lat": 11.5325558,
      "lon": 76.2418756,
      "type": "water"
    },
    {
      "id": 886863408,
      "lat": 11.5283002,
      "lon": 76.2398032,
      "type": "water"
    },
    {
      "id": 891252241,
      "lat": 11.6320043,
      "lon": 76.0646095,
      "type": "farmland"
    },
    {
      "id": 891252269,
      "lat": 11.6276785,
      "lon": 76.0709107,
      "type": "residential"
    },
    {
      "id": 891252270,
      "lat": 11.626589,
      "lon": 76.071691,
      "type": "residential"
    },
    {
      "id": 891252271,
      "lat": 11.6281099,
      "lon": 76.071022,
      "type": "residential"
    },
    {
      "id": 891252272,
      "lat": 11.6279135,
      "lon": 76.0718417,
      "type": "residential"
    },
    {
      "id": 891252284,
      "lat": 11.6257272,
      "lon": 76.0723436,
      "type": "residential"
    },
    {
      "id": 891252307,
      "lat": 11.6232532,
      "lon": 76.0747793,
      "type": "farmland"
    },
    {
      "id": 891252308,
      "lat": 11.6223458,
      "lon": 76.0744669,
      "type": "farmland"
    },
    {
      "id": 891252311,
      "lat": 11.6233347,
      "lon": 76.0776405,
      "type": "residential"
    },
    {
      "id": 891252312,
      "lat": 11.6206262,
      "lon": 76.0833234,
      "type": "residential"
    },
    {
      "id": 891252313,
      "lat": 11.6260824,
      "lon": 76.0785557,
      "type": "water"
    },
    {
      "id": 891252315,
      "lat": 11.6242904,
      "lon": 76.0795042,
      "type": "residential"
    },
    {
      "id": 891252316,
      "lat": 11.6267686,
      "lon": 76.0777704,
      "type": "farmland"
    },
    {
      "id": 891252338,
      "lat": 11.6239884,
      "lon": 76.075463,
      "type": "water"
    },
    {
      "id": 891407814,
      "lat": 11.5596703,
      "lon": 76.1105367,
      "type": "residential"
    },
    {
      "id": 892546552,
      "lat": 11.6411513,
      "lon": 76.119128,
      "type": "farmland"
    },
    {
      "id": 892546553,
      "lat": 11.6388792,
      "lon": 76.1231357,
      "type": "farmland"
    },
    {
      "id": 892546554,
      "lat": 11.6404013,
      "lon": 76.1213572,
      "type": "water"
    },
    {
      "id": 892546555,
      "lat": 11.6382733,
      "lon": 76.1208434,
      "type": "farmland"
    },
    {
      "id": 892546556,
      "lat": 11.6335922,
      "lon": 76.1279674,
      "type": "farmland"
    },
    {
      "id": 892546557,
      "lat": 11.6348946,
      "lon": 76.128271,
      "type": "water"
    },
    {
      "id": 892546558,
      "lat": 11.6360504,
      "lon": 76.1281887,
      "type": "farmland"
    },
    {
      "id": 892546559,
      "lat": 11.6355288,
      "lon": 76.1279157,
      "type": "farmland"
    },
    {
      "id": 892546560,
      "lat": 11.6347881,
      "lon": 76.1241835,
      "type": "farmland"
    },
    {
      "id": 892546561,
      "lat": 11.6373528,
      "lon": 76.1263537,
      "type": "farmland"
    },
    {
      "id": 892546563,
      "lat": 11.6401613,
      "lon": 76.1296258,
      "type": "farmland"
    },
    {
      "id": 892546564,
      "lat": 11.6338416,
      "lon": 76.1370472,
      "type": "farmland"
    },
    {
      "id": 892546565,
      "lat": 11.6348127,
      "lon": 76.1376981,
      "type": "water"
    },
    {
      "id": 892546566,
      "lat": 11.6357403,
      "lon": 76.1377877,
      "type": "farmland"
    },
    {
      "id": 892546567,
      "lat": 11.6324982,
      "lon": 76.1407411,
      "type": "farmland"
    },
    {
      "id": 892546568,
      "lat": 11.6325188,
      "lon": 76.142206,
      "type": "farmland"
    },
    {
      "id": 892546569,
      "lat": 11.6333006,
      "lon": 76.1432737,
      "type": "farmland"
    },
    {
      "id": 892546578,
      "lat": 11.6233359,
      "lon": 76.1505621,
      "type": "farmland"
    },
    {
      "id": 892546579,
      "lat": 11.623137,
      "lon": 76.155218,
      "type": "farmland"
    },
    {
      "id": 892546580,
      "lat": 11.6230237,
      "lon": 76.1540829,
      "type": "residential"
    },
    {
      "id": 892546581,
      "lat": 11.6106512,
      "lon": 76.1548464,
      "type": "farmland"
    },
    {
      "id": 892546594,
      "lat": 11.6102615,
      "lon": 76.1568266,
      "type": "residential"
    },
    {
      "id": 892546595,
      "lat": 11.6173226,
      "lon": 76.1539384,
      "type": "farmland"
    },
    {
      "id": 892546596,
      "lat": 11.6221531,
      "lon": 76.1639708,
      "type": "farmland"
    },
    {
      "id": 892546597,
      "lat": 11.6252413,
      "lon": 76.1732899,
      "type": "farmland"
    },
    {
      "id": 892546598,
      "lat": 11.6333723,
      "lon": 76.1722173,
      "type": "farmland"
    },
    {
      "id": 892546599,
      "lat": 11.6310635,
      "lon": 76.1689621,
      "type": "farmland"
    },
    {
      "id": 892546600,
      "lat": 11.6327107,
      "lon": 76.1652155,
      "type": "farmland"
    },
    {
      "id": 892546601,
      "lat": 11.6345065,
      "lon": 76.1635168,
      "type": "farmland"
    },
    {
      "id": 892546602,
      "lat": 11.6413961,
      "lon": 76.1606158,
      "type": "farmland"
    },
    {
      "id": 892546603,
      "lat": 11.6467904,
      "lon": 76.1581139,
      "type": "farmland"
    },
    {
      "id": 892546612,
      "lat": 11.6460311,
      "lon": 76.148261,
      "type": "residential"
    },
    {
      "id": 892546620,
      "lat": 11.6400965,
      "lon": 76.1471008,
      "type": "water"
    },
    {
      "id": 892546630,
      "lat": 11.6305659,
      "lon": 76.1470758,
      "type": "farmland"
    },
    {
      "id": 892546631,
      "lat": 11.6238719,
      "lon": 76.1490438,
      "type": "farmland"
    },
    {
      "id": 892546636,
      "lat": 11.6215276,
      "lon": 76.1560947,
      "type": "residential"
    },
    {
      "id": 892546637,
      "lat": 11.6182898,
      "lon": 76.1566703,
      "type": "farmland"
    },
    {
      "id": 892546638,
      "lat": 11.6186819,
      "lon": 76.1573974,
      "type": "farmland"
    },
    {
      "id": 892546640,
      "lat": 11.6194069,
      "lon": 76.1522109,
      "type": "residential"
    },
    {
      "id": 892546641,
      "lat": 11.6184993,
      "lon": 76.1473043,
      "type": "farmland"
    },
    {
      "id": 892546642,
      "lat": 11.6186794,
      "lon": 76.144977,
      "type": "farmland"
    },
    {
      "id": 892546644,
      "lat": 11.6167554,
      "lon": 76.143735,
      "type": "farmland"
    },
    {
      "id": 892546645,
      "lat": 11.6165466,
      "lon": 76.1415717,
      "type": "farmland"
    },
    {
      "id": 892546647,
      "lat": 11.6176322,
      "lon": 76.1339648,
      "type": "farmland"
    },
    {
      "id": 892546648,
      "lat": 11.6213917,
      "lon": 76.1364371,
      "type": "farmland"
    },
    {
      "id": 892560320,
      "lat": 11.622292,
      "lon": 76.1323757,
      "type": "farmland"
    },
    {
      "id": 892560321,
      "lat": 11.6236395,
      "lon": 76.1324742,
      "type": "farmland"
    },
    {
      "id": 892560322,
      "lat": 11.6273204,
      "lon": 76.1357099,
      "type": "farmland"
    },
    {
      "id": 892560323,
      "lat": 11.6260313,
      "lon": 76.1333211,
      "type": "farmland"
    },
    {
      "id": 892560324,
      "lat": 11.6230565,
      "lon": 76.1338114,
      "type": "farmland"
    },
    {
      "id": 892560329,
      "lat": 11.6208267,
      "lon": 76.1345349,
      "type": "farmland"
    },
    {
      "id": 892560330,
      "lat": 11.6145539,
      "lon": 76.1364056,
      "type": "farmland"
    },
    {
      "id": 892560331,
      "lat": 11.614098,
      "lon": 76.1345513,
      "type": "farmland"
    },
    {
      "id": 892560336,
      "lat": 11.6154133,
      "lon": 76.1345812,
      "type": "farmland"
    },
    {
      "id": 892560340,
      "lat": 11.6159178,
      "lon": 76.1287353,
      "type": "orchard"
    },
    {
      "id": 892560341,
      "lat": 11.6130771,
      "lon": 76.1294438,
      "type": "farmland"
    },
    {
      "id": 892560344,
      "lat": 11.612467,
      "lon": 76.1292509,
      "type": "farmland"
    },
    {
      "id": 892560348,
      "lat": 11.6065013,
      "lon": 76.1316415,
      "type": "farmland"
    },
    {
      "id": 892560349,
      "lat": 11.6072806,
      "lon": 76.1332205,
      "type": "farmland"
    },
    {
      "id": 892560350,
      "lat": 11.609112,
      "lon": 76.1333202,
      "type": "farmland"
    },
    {
      "id": 892560353,
      "lat": 11.6095684,
      "lon": 76.150929,
      "type": "farmland"
    },
    {
      "id": 892560361,
      "lat": 11.6055619,
      "lon": 76.1447688,
      "type": "farmland"
    },
    {
      "id": 892560364,
      "lat": 11.6066186,
      "lon": 76.1433774,
      "type": "water"
    },
    {
      "id": 892560365,
      "lat": 11.6100644,
      "lon": 76.143498,
      "type": "farmland"
    },
    {
      "id": 892560371,
      "lat": 11.6165217,
      "lon": 76.1300601,
      "type": "residential"
    },
    {
      "id": 892560378,
      "lat": 11.6141951,
      "lon": 76.1272306,
      "type": "residential"
    },
    {
      "id": 892560379,
      "lat": 11.5768168,
      "lon": 76.0695985,
      "type": "farmland"
    },
    {
      "id": 892560380,
      "lat": 11.5776919,
      "lon": 76.0649775,
      "type": "farmland"
    },
    {
      "id": 892560381,
      "lat": 11.5768998,
      "lon": 76.054627,
      "type": "farmland"
    },
    {
      "id": 892560411,
      "lat": 11.5840989,
      "lon": 76.0513169,
      "type": "residential"
    },
    {
      "id": 892560415,
      "lat": 11.5849598,
      "lon": 76.0546188,
      "type": "residential"
    },
    {
      "id": 892688341,
      "lat": 11.6342482,
      "lon": 76.109124,
      "type": "farmland"
    },
    {
      "id": 892688342,
      "lat": 11.6326698,
      "lon": 76.10928,
      "type": "farmland"
    },
    {
      "id": 892688343,
      "lat": 11.6327755,
      "lon": 76.1100313,
      "type": "water"
    },
    {
      "id": 892688344,
      "lat": 11.6318221,
      "lon": 76.1084333,
      "type": "water"
    },
    {
      "id": 892688345,
      "lat": 11.6321952,
      "lon": 76.1079409,
      "type": "farmland"
    },
    {
      "id": 892688348,
      "lat": 11.6333867,
      "lon": 76.1068706,
      "type": "farmland"
    },
    {
      "id": 892688349,
      "lat": 11.6359495,
      "lon": 76.1103325,
      "type": "farmland"
    },
    {
      "id": 892688353,
      "lat": 11.6361098,
      "lon": 76.1117665,
      "type": "farmland"
    },
    {
      "id": 892688357,
      "lat": 11.6359138,
      "lon": 76.1134848,
      "type": "residential"
    },
    {
      "id": 892688358,
      "lat": 11.6346196,
      "lon": 76.1034198,
      "type": "farmland"
    },
    {
      "id": 892688359,
      "lat": 11.6347843,
      "lon": 76.1049524,
      "type": "farmland"
    },
    {
      "id": 892688360,
      "lat": 11.6395572,
      "lon": 76.1066113,
      "type": "farmland"
    },
    {
      "id": 892688361,
      "lat": 11.6387578,
      "lon": 76.1056076,
      "type": "water"
    },
    {
      "id": 892688362,
      "lat": 11.6387543,
      "lon": 76.1065447,
      "type": "farmland"
    },
    {
      "id": 892688363,
      "lat": 11.6387063,
      "lon": 76.1081667,
      "type": "farmland"
    },
    {
      "id": 892688364,
      "lat": 11.6391935,
      "lon": 76.1097625,
      "type": "farmland"
    },
    {
      "id": 892688365,
      "lat": 11.6375084,
      "lon": 76.1085648,
      "type": "water"
    },
    {
      "id": 892688366,
      "lat": 11.6377636,
      "lon": 76.1081946,
      "type": "water"
    },
    {
      "id": 892688367,
      "lat": 11.6404839,
      "lon": 76.1100986,
      "type": "farmland"
    },
    {
      "id": 892688368,
      "lat": 11.6380166,
      "lon": 76.1115894,
      "type": "farmland"
    },
    {
      "id": 892688369,
      "lat": 11.6372817,
      "lon": 76.1158896,
      "type": "farmland"
    },
    {
      "id": 892688370,
      "lat": 11.6385948,
      "lon": 76.1185686,
      "type": "water"
    },
    {
      "id": 892688371,
      "lat": 11.6379539,
      "lon": 76.118389,
      "type": "farmland"
    },
    {
      "id": 892688372,
      "lat": 11.6412428,
      "lon": 76.1212537,
      "type": "farmland"
    },
    {
      "id": 892688373,
      "lat": 11.6364131,
      "lon": 76.1242686,
      "type": "farmland"
    },
    {
      "id": 892688377,
      "lat": 11.6367936,
      "lon": 76.1303717,
      "type": "farmland"
    },
    {
      "id": 892688378,
      "lat": 11.6276235,
      "lon": 76.1415649,
      "type": "farmland"
    },
    {
      "id": 892688379,
      "lat": 11.618018,
      "lon": 76.1426481,
      "type": "farmland"
    },
    {
      "id": 892688385,
      "lat": 11.6229101,
      "lon": 76.1584634,
      "type": "farmland"
    },
    {
      "id": 892688386,
      "lat": 11.6238991,
      "lon": 76.1604376,
      "type": "farmland"
    },
    {
      "id": 892688390,
      "lat": 11.6234438,
      "lon": 76.1667231,
      "type": "farmland"
    },
    {
      "id": 892688392,
      "lat": 11.6291791,
      "lon": 76.1679119,
      "type": "farmland"
    },
    {
      "id": 892688393,
      "lat": 11.6283854,
      "lon": 76.1690516,
      "type": "farmland"
    },
    {
      "id": 892688394,
      "lat": 11.6283211,
      "lon": 76.1689142,
      "type": "water"
    },
    {
      "id": 892688395,
      "lat": 11.6284218,
      "lon": 76.1691215,
      "type": "water"
    },
    {
      "id": 892688396,
      "lat": 11.6249639,
      "lon": 76.1704968,
      "type": "farmland"
    },
    {
      "id": 892688397,
      "lat": 11.6237892,
      "lon": 76.1707587,
      "type": "farmland"
    },
    {
      "id": 892688398,
      "lat": 11.6240543,
      "lon": 76.171712,
      "type": "farmland"
    },
    {
      "id": 892688400,
      "lat": 11.6222743,
      "lon": 76.1801575,
      "type": "farmland"
    },
    {
      "id": 892688401,
      "lat": 11.6221869,
      "lon": 76.1858083,
      "type": "farmland"
    },
    {
      "id": 892688402,
      "lat": 11.6198432,
      "lon": 76.1885618,
      "type": "farmland"
    },
    {
      "id": 892688406,
      "lat": 11.6200093,
      "lon": 76.192532,
      "type": "farmland"
    },
    {
      "id": 892688407,
      "lat": 11.6195592,
      "lon": 76.1937999,
      "type": "farmland"
    },
    {
      "id": 892688409,
      "lat": 11.6170828,
      "lon": 76.1953295,
      "type": "water"
    },
    {
      "id": 892688411,
      "lat": 11.6141845,
      "lon": 76.1962536,
      "type": "residential"
    },
    {
      "id": 892688412,
      "lat": 11.6142375,
      "lon": 76.1948305,
      "type": "residential"
    },
    {
      "id": 892688413,
      "lat": 11.6140601,
      "lon": 76.1932478,
      "type": "farmland"
    },
    {
      "id": 892688420,
      "lat": 11.6215701,
      "lon": 76.1909517,
      "type": "orchard"
    },
    {
      "id": 892930092,
      "lat": 11.6503522,
      "lon": 76.2298258,
      "type": "farmland"
    },
    {
      "id": 892930094,
      "lat": 11.6482549,
      "lon": 76.2279931,
      "type": "farmland"
    },
    {
      "id": 892930095,
      "lat": 11.6471212,
      "lon": 76.2254554,
      "type": "farmland"
    },
    {
      "id": 892930096,
      "lat": 11.6478551,
      "lon": 76.2223473,
      "type": "orchard"
    },
    {
      "id": 892930097,
      "lat": 11.6476166,
      "lon": 76.2162972,
      "type": "farmland"
    },
    {
      "id": 892930098,
      "lat": 11.6468618,
      "lon": 76.214006,
      "type": "farmland"
    },
    {
      "id": 892930099,
      "lat": 11.6478655,
      "lon": 76.2107284,
      "type": "water"
    },
    {
      "id": 892930100,
      "lat": 11.6494934,
      "lon": 76.2108718,
      "type": "farmland"
    },
    {
      "id": 892930101,
      "lat": 11.6499258,
      "lon": 76.2085158,
      "type": "farmland"
    },
    {
      "id": 892930102,
      "lat": 11.6417081,
      "lon": 76.2100784,
      "type": "orchard"
    },
    {
      "id": 892930103,
      "lat": 11.6428995,
      "lon": 76.2093158,
      "type": "water"
    },
    {
      "id": 892930104,
      "lat": 11.6431438,
      "lon": 76.2026929,
      "type": "water"
    },
    {
      "id": 892930105,
      "lat": 11.6436862,
      "lon": 76.2027236,
      "type": "water"
    },
    {
      "id": 892930106,
      "lat": 11.6429088,
      "lon": 76.2019739,
      "type": "farmland"
    },
    {
      "id": 892930107,
      "lat": 11.6419773,
      "lon": 76.2014617,
      "type": "water"
    },
    {
      "id": 892930108,
      "lat": 11.6420781,
      "lon": 76.2012078,
      "type": "farmland"
    },
    {
      "id": 892930109,
      "lat": 11.6450491,
      "lon": 76.2033482,
      "type": "farmland"
    },
    {
      "id": 892930110,
      "lat": 11.6388142,
      "lon": 76.1984619,
      "type": "water"
    },
    {
      "id": 892930111,
      "lat": 11.6387634,
      "lon": 76.1988869,
      "type": "water"
    },
    {
      "id": 892930112,
      "lat": 11.6387828,
      "lon": 76.1994509,
      "type": "farmland"
    },
    {
      "id": 892930113,
      "lat": 11.6440819,
      "lon": 76.1770702,
      "type": "farmland"
    },
    {
      "id": 892930114,
      "lat": 11.6479222,
      "lon": 76.1732106,
      "type": "farmland"
    },
    {
      "id": 892930115,
      "lat": 11.6475723,
      "lon": 76.1719143,
      "type": "farmland"
    },
    {
      "id": 892930116,
      "lat": 11.6491722,
      "lon": 76.1716131,
      "type": "farmland"
    },
    {
      "id": 892930117,
      "lat": 11.6485998,
      "lon": 76.1744415,
      "type": "farmland"
    },
    {
      "id": 892930118,
      "lat": 11.6479653,
      "lon": 76.1757026,
      "type": "farmland"
    },
    {
      "id": 892930119,
      "lat": 11.6503728,
      "lon": 76.1707306,
      "type": "farmland"
    },
    {
      "id": 892930120,
      "lat": 11.6493151,
      "lon": 76.1693197,
      "type": "farmland"
    },
    {
      "id": 892930121,
      "lat": 11.6487803,
      "lon": 76.1697945,
      "type": "orchard"
    },
    {
      "id": 892930122,
      "lat": 11.6466865,
      "lon": 76.1690946,
      "type": "farmland"
    },
    {
      "id": 892930123,
      "lat": 11.6472503,
      "lon": 76.1693985,
      "type": "farmland"
    },
    {
      "id": 892930124,
      "lat": 11.6466058,
      "lon": 76.164998,
      "type": "orchard"
    },
    {
      "id": 892930125,
      "lat": 11.6478876,
      "lon": 76.1554493,
      "type": "farmland"
    },
    {
      "id": 892930126,
      "lat": 11.649061,
      "lon": 76.1543348,
      "type": "farmland"
    },
    {
      "id": 893004037,
      "lat": 11.6447244,
      "lon": 76.0694386,
      "type": "farmland"
    },
    {
      "id": 893004038,
      "lat": 11.631405,
      "lon": 76.0784525,
      "type": "farmland"
    },
    {
      "id": 893004039,
      "lat": 11.6213441,
      "lon": 76.0670498,
      "type": "farmland"
    },
    {
      "id": 893004040,
      "lat": 11.6190334,
      "lon": 76.0692414,
      "type": "water"
    },
    {
      "id": 893004041,
      "lat": 11.6183031,
      "lon": 76.0689825,
      "type": "orchard"
    },
    {
      "id": 893004043,
      "lat": 11.6224456,
      "lon": 76.0497119,
      "type": "farmland"
    },
    {
      "id": 893004044,
      "lat": 11.6246383,
      "lon": 76.0517926,
      "type": "water"
    },
    {
      "id": 893591489,
      "lat": 11.6500265,
      "lon": 76.1766349,
      "type": "farmland"
    },
    {
      "id": 893591490,
      "lat": 11.6281203,
      "lon": 76.1799386,
      "type": "farmland"
    },
    {
      "id": 893591491,
      "lat": 11.6253284,
      "lon": 76.1965347,
      "type": "farmland"
    },
    {
      "id": 893591492,
      "lat": 11.6016701,
      "lon": 76.1352904,
      "type": "farmland"
    },
    {
      "id": 893591493,
      "lat": 11.602159,
      "lon": 76.1375318,
      "type": "farmland"
    },
    {
      "id": 893591494,
      "lat": 11.6009342,
      "lon": 76.137221,
      "type": "farmland"
    },
    {
      "id": 893591495,
      "lat": 11.6002157,
      "lon": 76.138038,
      "type": "farmland"
    },
    {
      "id": 893591496,
      "lat": 11.6007483,
      "lon": 76.1390876,
      "type": "farmland"
    },
    {
      "id": 893591497,
      "lat": 11.5986153,
      "lon": 76.141869,
      "type": "farmland"
    },
    {
      "id": 893591498,
      "lat": 11.5970686,
      "lon": 76.1365692,
      "type": "farmland"
    },
    {
      "id": 893591499,
      "lat": 11.5968685,
      "lon": 76.1377289,
      "type": "farmland"
    },
    {
      "id": 893591500,
      "lat": 11.5969486,
      "lon": 76.1401604,
      "type": "farmland"
    },
    {
      "id": 893591501,
      "lat": 11.5916931,
      "lon": 76.1501511,
      "type": "farmland"
    },
    {
      "id": 893591502,
      "lat": 11.5868122,
      "lon": 76.1451609,
      "type": "farmland"
    },
    {
      "id": 893591503,
      "lat": 11.5892626,
      "lon": 76.1474396,
      "type": "farmland"
    },
    {
      "id": 893591504,
      "lat": 11.588705,
      "lon": 76.1491647,
      "type": "farmland"
    },
    {
      "id": 893591505,
      "lat": 11.5829246,
      "lon": 76.1451482,
      "type": "farmland"
    },
    {
      "id": 893591506,
      "lat": 11.5736677,
      "lon": 76.1240949,
      "type": "farmland"
    },
    {
      "id": 893591507,
      "lat": 11.5723123,
      "lon": 76.1245933,
      "type": "farmland"
    },
    {
      "id": 893591508,
      "lat": 11.6033278,
      "lon": 76.0608258,
      "type": "farmland"
    },
    {
      "id": 893591509,
      "lat": 11.6065278,
      "lon": 76.0654973,
      "type": "farmland"
    },
    {
      "id": 894632989,
      "lat": 11.6497395,
      "lon": 76.0532788,
      "type": "farmland"
    },
    {
      "id": 894632991,
      "lat": 11.6499732,
      "lon": 76.0544438,
      "type": "water"
    },
    {
      "id": 894632992,
      "lat": 11.6495826,
      "lon": 76.0564656,
      "type": "orchard"
    },
    {
      "id": 894632993,
      "lat": 11.6487374,
      "lon": 76.0548369,
      "type": "orchard"
    },
    {
      "id": 894632994,
      "lat": 11.6480273,
      "lon": 76.0557253,
      "type": "water"
    },
    {
      "id": 894632995,
      "lat": 11.6479486,
      "lon": 76.0531814,
      "type": "orchard"
    },
    {
      "id": 894632996,
      "lat": 11.6483074,
      "lon": 76.0540774,
      "type": "orchard"
    },
    {
      "id": 894632997,
      "lat": 11.6467769,
      "lon": 76.0539251,
      "type": "orchard"
    },
    {
      "id": 894632998,
      "lat": 11.6450444,
      "lon": 76.0548583,
      "type": "water"
    },
    {
      "id": 894632999,
      "lat": 11.6438598,
      "lon": 76.0586136,
      "type": "water"
    },
    {
      "id": 894633000,
      "lat": 11.6437009,
      "lon": 76.0580522,
      "type": "farmland"
    },
    {
      "id": 894633001,
      "lat": 11.6441647,
      "lon": 76.0597249,
      "type": "orchard"
    },
    {
      "id": 894633002,
      "lat": 11.6359592,
      "lon": 76.0521009,
      "type": "water"
    },
    {
      "id": 894633003,
      "lat": 11.6323037,
      "lon": 76.0528378,
      "type": "farmland"
    },
    {
      "id": 894633004,
      "lat": 11.6311411,
      "lon": 76.05575,
      "type": "farmland"
    },
    {
      "id": 894633005,
      "lat": 11.6269902,
      "lon": 76.052166,
      "type": "quarry"
    },
    {
      "id": 904936320,
      "lat": 11.555312,
      "lon": 76.1611093,
      "type": "residential"
    },
    {
      "id": 904941247,
      "lat": 11.5511141,
      "lon": 76.1577477,
      "type": "residential"
    },
    {
      "id": 904941833,
      "lat": 11.551698,
      "lon": 76.161293,
      "type": "residential"
    },
    {
      "id": 913703580,
      "lat": 11.6503607,
      "lon": 76.1351328,
      "type": "farmland"
    },
    {
      "id": 913703761,
      "lat": 11.650313,
      "lon": 76.1342079,
      "type": "farmland"
    },
    {
      "id": 934323286,
      "lat": 11.6318599,
      "lon": 76.1046132,
      "type": "residential"
    },
    {
      "id": 934982578,
      "lat": 11.627685,
      "lon": 76.1646478,
      "type": "residential"
    },
    {
      "id": 934984670,
      "lat": 11.6133105,
      "lon": 76.1521489,
      "type": "residential"
    },
    {
      "id": 934987276,
      "lat": 11.6457174,
      "lon": 76.1570875,
      "type": "residential"
    },
    {
      "id": 934987761,
      "lat": 11.6427931,
      "lon": 76.1140884,
      "type": "residential"
    },
    {
      "id": 935072528,
      "lat": 11.6453441,
      "lon": 76.120655,
      "type": "residential"
    },
    {
      "id": 935072925,
      "lat": 11.6453596,
      "lon": 76.1197603,
      "type": "residential"
    },
    {
      "id": 935104226,
      "lat": 11.6460357,
      "lon": 76.0932816,
      "type": "residential"
    },
    {
      "id": 935500101,
      "lat": 11.621743,
      "lon": 76.1614188,
      "type": "residential"
    },
    {
      "id": 935502608,
      "lat": 11.6183672,
      "lon": 76.1576367,
      "type": "residential"
    },
    {
      "id": 935506556,
      "lat": 11.6103243,
      "lon": 76.1624012,
      "type": "residential"
    },
    {
      "id": 935517093,
      "lat": 11.6117558,
      "lon": 76.1525755,
      "type": "residential"
    },
    {
      "id": 935527635,
      "lat": 11.6289445,
      "lon": 76.1471102,
      "type": "residential"
    },
    {
      "id": 935685545,
      "lat": 11.6359305,
      "lon": 76.1091021,
      "type": "residential"
    },
    {
      "id": 935692257,
      "lat": 11.6338356,
      "lon": 76.0968621,
      "type": "residential"
    },
    {
      "id": 935922408,
      "lat": 11.641884,
      "lon": 76.1543132,
      "type": "residential"
    },
    {
      "id": 936313316,
      "lat": 11.5306176,
      "lon": 76.1385753,
      "type": "wood"
    },
    {
      "id": 936313319,
      "lat": 11.502963,
      "lon": 76.1428972,
      "type": "orchard"
    },
    {
      "id": 939336773,
      "lat": 11.5891293,
      "lon": 76.2091185,
      "type": "recreation_ground"
    },
    {
      "id": 954185114,
      "lat": 11.5710974,
      "lon": 76.0514584,
      "type": "recreation_ground"
    },
    {
      "id": 955308358,
      "lat": 11.5663776,
      "lon": 76.0505265,
      "type": "orchard"
    },
    {
      "id": 956029181,
      "lat": 11.5788503,
      "lon": 76.06421,
      "type": "cemetery"
    },
    {
      "id": 956118761,
      "lat": 11.6443692,
      "lon": 76.2487085,
      "type": "greenfield"
    },
    {
      "id": 956120880,
      "lat": 11.639835,
      "lon": 76.2393579,
      "type": "farmland"
    },
    {
      "id": 956349953,
      "lat": 11.5861161,
      "lon": 76.0633786,
      "type": "industrial"
    },
    {
      "id": 956357580,
      "lat": 11.5468061,
      "lon": 76.0498175,
      "type": "orchard"
    },
    {
      "id": 959163798,
      "lat": 11.57453,
      "lon": 76.0551427,
      "type": "residential"
    },
    {
      "id": 960659330,
      "lat": 11.557845,
      "lon": 76.0612387,
      "type": "residential"
    },
    {
      "id": 962637550,
      "lat": 11.6072639,
      "lon": 76.069795,
      "type": "residential"
    },
    {
      "id": 979523929,
      "lat": 11.6464981,
      "lon": 76.1662728,
      "type": "residential"
    },
    {
      "id": 979526225,
      "lat": 11.6469911,
      "lon": 76.1759749,
      "type": "residential"
    },
    {
      "id": 979748665,
      "lat": 11.6502741,
      "lon": 76.1595199,
      "type": "residential"
    },
    {
      "id": 979748667,
      "lat": 11.6499412,
      "lon": 76.1572257,
      "type": "residential"
    },
    {
      "id": 979779182,
      "lat": 11.6435156,
      "lon": 76.2069293,
      "type": "residential"
    },
    {
      "id": 979779183,
      "lat": 11.6465014,
      "lon": 76.2057779,
      "type": "residential"
    },
    {
      "id": 979964490,
      "lat": 11.6500396,
      "lon": 76.1858989,
      "type": "residential"
    },
    {
      "id": 980134383,
      "lat": 11.6485211,
      "lon": 76.1777438,
      "type": "residential"
    },
    {
      "id": 980134386,
      "lat": 11.6494515,
      "lon": 76.1740931,
      "type": "residential"
    },
    {
      "id": 980134387,
      "lat": 11.6502133,
      "lon": 76.1718503,
      "type": "residential"
    },
    {
      "id": 980149753,
      "lat": 11.6430761,
      "lon": 76.1668322,
      "type": "residential"
    },
    {
      "id": 980149754,
      "lat": 11.6387052,
      "lon": 76.1622952,
      "type": "residential"
    },
    {
      "id": 981148194,
      "lat": 11.6487798,
      "lon": 76.1307616,
      "type": "plant_nursery"
    },
    {
      "id": 981149905,
      "lat": 11.6481838,
      "lon": 76.1347763,
      "type": "plant_nursery"
    },
    {
      "id": 982923329,
      "lat": 11.6435981,
      "lon": 76.0695561,
      "type": "residential"
    },
    {
      "id": 982923330,
      "lat": 11.6455681,
      "lon": 76.0607448,
      "type": "residential"
    },
    {
      "id": 982923331,
      "lat": 11.645407,
      "lon": 76.0546514,
      "type": "residential"
    },
    {
      "id": 994962301,
      "lat": 11.6487662,
      "lon": 76.1392819,
      "type": "farmland"
    },
    {
      "id": 997186751,
      "lat": 11.4897998,
      "lon": 76.1550594,
      "type": "recreation_ground"
    },
    {
      "id": 1018145305,
      "lat": 11.5402467,
      "lon": 76.1753408,
      "type": "recreation_ground"
    },
    {
      "id": 1018145640,
      "lat": 11.5483011,
      "lon": 76.1787018,
      "type": "recreation_ground"
    },
    {
      "id": 1018146009,
      "lat": 11.5469838,
      "lon": 76.2037481,
      "type": "recreation_ground"
    },
    {
      "id": 1018146140,
      "lat": 11.5397767,
      "lon": 76.1600974,
      "type": "recreation_ground"
    },
    {
      "id": 1018276782,
      "lat": 11.4519363,
      "lon": 76.2546923,
      "type": "residential"
    },
    {
      "id": 1032070518,
      "lat": 11.5434128,
      "lon": 76.0626733,
      "type": "orchard"
    },
    {
      "id": 1032070520,
      "lat": 11.552805,
      "lon": 76.1091077,
      "type": "orchard"
    },
    {
      "id": 1040818360,
      "lat": 11.6483017,
      "lon": 76.1372535,
      "type": "water"
    },
    {
      "id": 1040818684,
      "lat": 11.6475421,
      "lon": 76.1362211,
      "type": "water"
    },
    {
      "id": 1095788231,
      "lat": 11.5499693,
      "lon": 76.0579337,
      "type": "water"
    },
    {
      "id": 1098173189,
      "lat": 11.5459686,
      "lon": 76.0503066,
      "type": "water"
    },
    {
      "id": 1103374875,
      "lat": 11.6468085,
      "lon": 76.2275157,
      "type": "residential"
    },
    {
      "id": 1103423855,
      "lat": 11.6368832,
      "lon": 76.248014,
      "type": "residential"
    },
    {
      "id": 1104867432,
      "lat": 11.6310186,
      "lon": 76.0520511,
      "type": "residential"
    },
    {
      "id": 1104869428,
      "lat": 11.621552,
      "lon": 76.0638555,
      "type": "residential"
    },
    {
      "id": 1104878999,
      "lat": 11.6306389,
      "lon": 76.0814775,
      "type": "residential"
    },
    {
      "id": 1104914770,
      "lat": 11.6153685,
      "lon": 76.0626931,
      "type": "residential"
    },
    {
      "id": 1104915029,
      "lat": 11.6195749,
      "lon": 76.0654565,
      "type": "residential"
    },
    {
      "id": 1104925583,
      "lat": 11.620415,
      "lon": 76.079031,
      "type": "residential"
    },
    {
      "id": 1105119554,
      "lat": 11.6226454,
      "lon": 76.0650818,
      "type": "residential"
    },
    {
      "id": 1105120622,
      "lat": 11.6400548,
      "lon": 76.0841325,
      "type": "residential"
    },
    {
      "id": 1105120776,
      "lat": 11.6392748,
      "lon": 76.0836865,
      "type": "residential"
    },
    {
      "id": 1105134236,
      "lat": 11.6391885,
      "lon": 76.0907399,
      "type": "residential"
    },
    {
      "id": 1105150183,
      "lat": 11.632847,
      "lon": 76.0669495,
      "type": "residential"
    },
    {
      "id": 1105151267,
      "lat": 11.6471266,
      "lon": 76.0767322,
      "type": "residential"
    },
    {
      "id": 1105152463,
      "lat": 11.6189536,
      "lon": 76.0787875,
      "type": "residential"
    },
    {
      "id": 1105157244,
      "lat": 11.5887744,
      "lon": 76.0770234,
      "type": "residential"
    },
    {
      "id": 1105157435,
      "lat": 11.591367,
      "lon": 76.0777524,
      "type": "residential"
    },
    {
      "id": 1105157568,
      "lat": 11.5936732,
      "lon": 76.0813057,
      "type": "residential"
    },
    {
      "id": 1105164061,
      "lat": 11.5821146,
      "lon": 76.0674858,
      "type": "residential"
    },
    {
      "id": 1105168829,
      "lat": 11.5862387,
      "lon": 76.1004636,
      "type": "residential"
    },
    {
      "id": 1105169004,
      "lat": 11.5855939,
      "lon": 76.0940866,
      "type": "residential"
    },
    {
      "id": 1105169125,
      "lat": 11.5823975,
      "lon": 76.0940245,
      "type": "residential"
    },
    {
      "id": 1107629900,
      "lat": 11.6336116,
      "lon": 76.2114167,
      "type": "recreation_ground"
    },
    {
      "id": 1107630535,
      "lat": 11.6377765,
      "lon": 76.1740275,
      "type": "recreation_ground"
    },
    {
      "id": 1111936994,
      "lat": 11.6049263,
      "lon": 76.0576704,
      "type": "residential"
    },
    {
      "id": 1111937324,
      "lat": 11.6078645,
      "lon": 76.0596438,
      "type": "residential"
    },
    {
      "id": 1111937983,
      "lat": 11.6006428,
      "lon": 76.0631463,
      "type": "residential"
    },
    {
      "id": 1111938161,
      "lat": 11.59711,
      "lon": 76.0691744,
      "type": "residential"
    },
    {
      "id": 1111939004,
      "lat": 11.6042937,
      "lon": 76.066185,
      "type": "residential"
    },
    {
      "id": 1117764044,
      "lat": 11.6461731,
      "lon": 76.0728616,
      "type": "water"
    },
    {
      "id": 1148405023,
      "lat": 11.5144819,
      "lon": 76.1400802,
      "type": "water"
    },
    {
      "id": 1149213707,
      "lat": 11.5473002,
      "lon": 76.0827819,
      "type": "water"
    },
    {
      "id": 1149213964,
      "lat": 11.5494597,
      "lon": 76.0841733,
      "type": "water"
    },
    {
      "id": 1153989358,
      "lat": 11.490662,
      "lon": 76.2896818,
      "type": "wood"
    },
    {
      "id": 1153989359,
      "lat": 11.5170266,
      "lon": 76.1928147,
      "type": "wood"
    },
    {
      "id": 1198549095,
      "lat": 11.62588,
      "lon": 76.1994128,
      "type": "water"
    },
    {
      "id": 1226389303,
      "lat": 11.6309815,
      "lon": 76.1579119,
      "type": "water"
    },
    {
      "id": 1226435381,
      "lat": 11.6190422,
      "lon": 76.1709021,
      "type": "water"
    },
    {
      "id": 1243123898,
      "lat": 11.5566939,
      "lon": 76.0573653,
      "type": "water"
    },
    {
      "id": 1243323776,
      "lat": 11.5861949,
      "lon": 76.0974257,
      "type": "religious"
    },
    {
      "id": 1304758264,
      "lat": 11.5010172,
      "lon": 76.1673218,
      "type": "farmland"
    },
    {
      "id": 1304758267,
      "lat": 11.5005191,
      "lon": 76.1675391,
      "type": "farmland"
    },
    {
      "id": 1304875829,
      "lat": 11.50274,
      "lon": 76.1514917,
      "type": "wood"
    },
    {
      "id": 1304953160,
      "lat": 11.483737,
      "lon": 76.167888,
      "type": "orchard"
    },
    {
      "id": 1305339297,
      "lat": 11.5829243,
      "lon": 76.1354173,
      "type": "water"
    },
    {
      "id": 1308483807,
      "lat": 11.5085258,
      "lon": 76.1497861,
      "type": "water"
    },
    {
      "id": 1315250064,
      "lat": 11.6287094,
      "lon": 76.0526091,
      "type": "water"
    },
    {
      "id": 1315252072,
      "lat": 11.6253042,
      "lon": 76.051617,
      "type": "residential"
    },
    {
      "id": 1332641197,
      "lat": 11.5198811,
      "lon": 76.0648942,
      "type": "orchard"
    },
    {
      "id": 1334633836,
      "lat": 11.5440222,
      "lon": 76.0507977,
      "type": "residential"
    },
    {
      "id": 1334648388,
      "lat": 11.5508002,
      "lon": 76.0498812,
      "type": "wood"
    },
    {
      "id": 1347557912,
      "lat": 11.4867127,
      "lon": 76.1554342,
      "type": "religious"
    },
    {
      "id": 1396049835,
      "lat": 11.6325795,
      "lon": 76.1057693,
      "type": "religious"
    },
    {
      "id": 1402498798,
      "lat": 11.5879493,
      "lon": 76.2218793,
      "type": "water"
    },
    {
      "id": 1410322225,
      "lat": 11.5351568,
      "lon": 76.2462992,
      "type": "farmland"
    },
    {
      "id": 1410323534,
      "lat": 11.5391225,
      "lon": 76.2474488,
      "type": "farmland"
    },
    {
      "id": 1427125627,
      "lat": 11.5182486,
      "lon": 76.1213391,
      "type": "water"
    }
  ],
  "bbox": {
    "min_lat": 11.45,
    "max_lat": 11.65,
    "min_lon": 76.05,
    "max_lon": 76.25
  }
}